TestUm/TestUm.py
TestUm/__init__.py
TestUm-0.2.dist-info/METADATA
TestUm-0.2.dist-info/WHEEL
TestUm-0.2.dist-info/top_level.txt
TestUm-0.2.dist-info/RECORD
